[{"owner":"virattt","name":"ai-hedge-fund","description":"An AI Hedge Fund Team","language":"Python","stars":10980,"forks":2138,"builtBy":["virattt","seungwonme","KittatamSaisaard","andorsk","arsaboo"],"starsToday":871},{"owner":"hashicorp","name":"terraform","description":"Terraform enables you to safely and predictably create, change, and improve infrastructure. It is a source-available tool that codifies APIs into declarative configuration files that can be shared amongst team members, treated as code, edited, reviewed, and versioned.","language":"Go","stars":44548,"forks":9730,"builtBy":["jbardin","mitchellh","apparentlymart","stack72","catsby"],"starsToday":126},{"owner":"unionlabs","name":"union","description":"The trust-minimized, zero-knowledge bridging protocol, designed for censorship resistance, extremely high security, and usage in decentralized finance.","language":"Rust","stars":40067,"forks":2156,"builtBy":["cor","benluelo","hussein-aitlahcen","o-az","PoisonPhang"],"starsToday":3399},{"owner":"grpc-ecosystem","name":"grpc-gateway","description":"gRPC to JSON proxy generator following the gRPC HTTP spec","language":"Go","stars":18718,"forks":2279,"builtBy":["renovate-bot","johanbrandhorst","yugui"],"starsToday":126},{"owner":"microsoft","name":"generative-ai-for-beginners","description":"21 Lessons, Get Started Building with Generative AI 🔗 https://microsoft.github.io/generative-ai-for-beginners/","language":"Jupyter Notebook","stars":72721,"forks":37770,"builtBy":["koreyspace","john0isaac","yoshioterada","leestott","glaucia86"],"starsToday":331},{"owner":"sadmann7","name":"shadcn-table","description":"Shadcn table with server-side sorting, filtering, and pagination.","language":"TypeScript","stars":3938,"forks":337,"builtBy":["sadmann7","kavinvalli","dBianchii","yuvarajmadineni"],"starsToday":85},{"owner":"clockworklabs","name":"SpacetimeDB","description":"Multiplayer at the speed of light","language":"Rust","stars":5322,"forks":134,"builtBy":["Centril","gefjon","joshua-spacetime","kim","RReverser"],"starsToday":472},{"owner":"gorhill","name":"uBlock","description":"uBlock Origin - An efficient blocker for Chromium and Firefox. Fast and lean.","language":"JavaScript","stars":50831,"forks":3335,"builtBy":["gorhill","Deathamns","chrisaljoudi","mjethani","AlexVallat"],"starsToday":376},{"owner":"microsoft","name":"PowerToys","description":"Windows system utilities to maximize productivity","language":"C#","stars":115381,"forks":6797,"builtBy":["crutkas","bao-qian","qianlifeng","jaimecbernardo","stefansjfw"],"starsToday":62},{"owner":"zigtools","name":"zls","description":"A Zig language server supporting Zig developers with features like autocomplete and goto definition","language":"Zig","stars":3414,"forks":328,"builtBy":["Techatrix","alexnask","SuperAuguste","leecannon","llogick"],"starsToday":11},{"owner":"Plachtaa","name":"seed-vc","description":"zero-shot voice conversion & singing voice conversion, with real-time support","language":"Python","stars":1211,"forks":149,"builtBy":["Plachtaa","justinjohn0306","yyahav","v3ucn","ppmzhang2"],"starsToday":13}]
